py_doubly_linked_list/__init__.py
py_doubly_linked_list/__init__.pyi
py_doubly_linked_list/doubly_linked_list.cp313-win32.pyd
py_doubly_linked_list/py.typed
py_doubly_linked_list-0.1.3.dist-info/licenses/LICENSE
py_doubly_linked_list-0.1.3.dist-info/licenses/README.MD
py_doubly_linked_list-0.1.3.dist-info/METADATA
py_doubly_linked_list-0.1.3.dist-info/WHEEL
py_doubly_linked_list-0.1.3.dist-info/top_level.txt
py_doubly_linked_list-0.1.3.dist-info/RECORD
