Metadata-Version: 2.4
Name: py-doubly-linked-list
Version: 0.1.3
Summary: A library adding doubly linked lists to python.
Author-email: Joshua Morningstar <joshuam18745@gmail.com>
Maintainer-email: Joshua Morningstar <joshuam18745@gmail.com>
License-Expression: MIT
Project-URL: Documentation, https://github.com/JoshuaM176/PyDoublyLinkedList/blob/main/README.MD
Project-URL: Repository, https://github.com/JoshuaM176/PyDoublyLinkedList
Project-URL: Issues, https://github.com/JoshuaM176/PyDoublyLinkedList/issues
Project-URL: Changelog, https://github.com/JoshuaM176/PyDoublyLinkedList/blob/main/CHANGES
Keywords: doubly linked list,data structure
Classifier: Development Status :: 5 - Production/Stable
Classifier: Intended Audience :: Developers
Classifier: Programming Language :: Python :: 3
Classifier: Programming Language :: Python :: 3.9
Classifier: Programming Language :: Python :: 3.10
Classifier: Programming Language :: Python :: 3.11
Classifier: Programming Language :: Python :: 3.12
Classifier: Programming Language :: Python :: 3.13
Classifier: Programming Language :: Python :: 3.14
Requires-Python: >=3.9
License-File: LICENSE
License-File: README.MD
Dynamic: license-file
